kern_smooth/__init__.py
kern_smooth/ks.py
kern_smooth-1.1.2.dist-info/LICENSE
kern_smooth-1.1.2.dist-info/METADATA
kern_smooth-1.1.2.dist-info/WHEEL
kern_smooth-1.1.2.dist-info/top_level.txt
kern_smooth-1.1.2.dist-info/RECORD
