Metadata-Version: 2.1
Name: kern-smooth
Version: 1.1.2
Summary: A python implementation of KernSmooth package (https://cran.r-project.org/web/packages/KernSmooth):kernel smoothing and density estimation functions based on the book: Wand, M.P. and Jones, M.C. (1995) "Kernel Smoothing".
Home-page: https://github.com/AlexanderButyaev/kern_smooth
Author: Alexander Butyaev
Author-email: alexander.butyaev@mail.mcgill.ca
License: MIT
Keywords: statistics,probability,KDE,PDF,kernel density estimation
License-File: LICENSE
Requires-Dist: numpy
Requires-Dist: pandas
Requires-Dist: scipy
